nanorm.py
nanorm_test.py
nanorm-1.8.5.dist-info/DESCRIPTION.rst
nanorm-1.8.5.dist-info/METADATA
nanorm-1.8.5.dist-info/RECORD
nanorm-1.8.5.dist-info/WHEEL
nanorm-1.8.5.dist-info/metadata.json
nanorm-1.8.5.dist-info/top_level.txt
