Metadata-Version: 2.0
Name: nanorm
Version: 1.8.5
Summary: A simple ORM framework for Python ( Nano ORM )
Home-page: https://github.com/taojy123/nanorm
Author: Tao Jiayuan
Author-email: taojy123@163.com
License: MIT
Keywords: orm namo mini sample database sqlite nanorm nanoorm
Platform: UNKNOWN
